pact_testgen/__init__.py
pact_testgen/broker.py
pact_testgen/cli.py
pact_testgen/files.py
pact_testgen/generator.py
pact_testgen/models.py
pact_testgen/pact_testgen.py
pact_testgen/public.py
pact_testgen/utils.py
pact_testgen/verify.py
pact_testgen/dialects/__init__.py
pact_testgen/dialects/base.py
pact_testgen/dialects/django.py
pact_testgen/dialects/templates/django/provider_states.jinja
pact_testgen/dialects/templates/django/test_case.jinja
pact_testgen/dialects/templates/django/test_file.jinja
pact_testgen/dialects/templates/django/test_methods.jinja
pact_testgen-0.7.0.dist-info/LICENSE
pact_testgen-0.7.0.dist-info/METADATA
pact_testgen-0.7.0.dist-info/WHEEL
pact_testgen-0.7.0.dist-info/entry_points.txt
pact_testgen-0.7.0.dist-info/top_level.txt
pact_testgen-0.7.0.dist-info/RECORD
