Metadata-Version: 2.1
Name: pact-testgen
Version: 0.7.0
Summary: Generate Python test cases from Pact files, for easier provider verification.
Home-page: https://github.com/pymetrics/pact-testgen
Author: Chris Lawlor
Author-email: chris@pymetrics.com
License: MIT license
Keywords: pact_testgen
Classifier: Development Status :: 2 - Pre-Alpha
Classifier: Intended Audience :: Developers
Classifier: License :: OSI Approved :: MIT License
Classifier: Natural Language :: English
Classifier: Programming Language :: Python :: 3
Classifier: Programming Language :: Python :: 3.7
Classifier: Programming Language :: Python :: 3.8
Classifier: Programming Language :: Python :: 3.9
Classifier: Programming Language :: Python :: 3.10
Classifier: Programming Language :: Python :: 3.11
Requires-Python: >=3.7
License-File: LICENSE
Requires-Dist: jinja2
Requires-Dist: pydantic <3,>=2
Requires-Dist: pactman
Requires-Dist: python-slugify
Requires-Dist: black
Requires-Dist: requests
